vedro_jira_failed_reporter/__init__.py
vedro_jira_failed_reporter/_failed_reporter_plugin.py
vedro_jira_failed_reporter/_jira_stdout.py
vedro_jira_failed_reporter/_messages.py
vedro_jira_failed_reporter/_traceback.py
vedro_jira_failed_reporter/py.typed
vedro_jira_failed_reporter/version
vedro_jira_failed_reporter/version.py
vedro_jira_failed_reporter-2.4.1.dist-info/LICENSE
vedro_jira_failed_reporter-2.4.1.dist-info/METADATA
vedro_jira_failed_reporter-2.4.1.dist-info/WHEEL
vedro_jira_failed_reporter-2.4.1.dist-info/top_level.txt
vedro_jira_failed_reporter-2.4.1.dist-info/RECORD
