Metadata-Version: 2.1
Name: vedro-jira-failed-reporter
Version: 2.4.1
Summary: vedro.io plugin for reporting about flaky tests into jira (with plugin enabled in flaky check runs)
Home-page: https://github.com/ko10ok/vedro-jira-failed-reporter
Author: Yuriy Sagitov
Author-email: pro100.ko10ok@gmail.com
License: Apache-2.0
Classifier: License :: OSI Approved :: Apache Software License
Classifier: Programming Language :: Python :: 3.10
Classifier: Typing :: Typed
Requires-Python: >=3.7
License-File: LICENSE
Requires-Dist: vedro<2.0,>=1.7
Requires-Dist: jira<3.7,>=3.6.0
Requires-Dist: rtry<2.0,>=1.4.0
